haystack_integrations/common/py.typed
haystack_integrations/common/amazon_bedrock/__init__.py
haystack_integrations/common/amazon_bedrock/errors.py
haystack_integrations/common/amazon_bedrock/utils.py
haystack_integrations/common/s3/__init__.py
haystack_integrations/common/s3/errors.py
haystack_integrations/common/s3/utils.py
haystack_integrations/components/downloaders/py.typed
haystack_integrations/components/downloaders/s3/__init__.py
haystack_integrations/components/downloaders/s3/s3_downloader.py
haystack_integrations/components/embedders/py.typed
haystack_integrations/components/embedders/amazon_bedrock/__init__.py
haystack_integrations/components/embedders/amazon_bedrock/document_embedder.py
haystack_integrations/components/embedders/amazon_bedrock/document_image_embedder.py
haystack_integrations/components/embedders/amazon_bedrock/text_embedder.py
haystack_integrations/components/generators/py.typed
haystack_integrations/components/generators/amazon_bedrock/__init__.py
haystack_integrations/components/generators/amazon_bedrock/adapters.py
haystack_integrations/components/generators/amazon_bedrock/generator.py
haystack_integrations/components/generators/amazon_bedrock/chat/__init__.py
haystack_integrations/components/generators/amazon_bedrock/chat/chat_generator.py
haystack_integrations/components/generators/amazon_bedrock/chat/utils.py
haystack_integrations/components/rankers/py.typed
haystack_integrations/components/rankers/amazon_bedrock/__init__.py
haystack_integrations/components/rankers/amazon_bedrock/ranker.py
amazon_bedrock_haystack-6.2.0.dist-info/METADATA
amazon_bedrock_haystack-6.2.0.dist-info/WHEEL
amazon_bedrock_haystack-6.2.0.dist-info/licenses/LICENSE.txt
amazon_bedrock_haystack-6.2.0.dist-info/RECORD
